fuwa/gateway/__init__.py
fuwa/gateway/connection.py
fuwa/gateway/heartbeat.py
fuwa/gateway/intents.py
gateway/__init__.py
gateway/connection.py
gateway/heartbeat.py
gateway/intents.py
fuwa_gateway-1.0.2a0.dist-info/METADATA
fuwa_gateway-1.0.2a0.dist-info/WHEEL
fuwa_gateway-1.0.2a0.dist-info/top_level.txt
fuwa_gateway-1.0.2a0.dist-info/RECORD
