Metadata-Version: 2.1
Name: fuwa-gateway
Version: 1.0.2a0
Summary: The gateway implementation for the fuwa eco-system
Home-page: https://github.com/fuwa-py/fuwa-gateway
Author: justanotherebyte
License: UNKNOWN
Project-URL: Issue Tracker, https://github.com/fuwa-py/fuwa-gateway/issues
Platform: UNKNOWN
Classifier: Development Status :: 3 - Alpha
Classifier: License :: OSI Approved :: MIT License
Classifier: Intended Audience :: Developers
Classifier: Natural Language :: English
Classifier: Operating System :: OS Independent
Classifier: Programming Language :: Python :: 3.8
Classifier: Programming Language :: Python :: 3.9
Classifier: Topic :: Internet
Classifier: Topic :: Software Development :: Libraries
Classifier: Topic :: Software Development :: Libraries :: Python Modules
Classifier: Topic :: Utilities
Classifier: Typing :: Typed
Requires-Python: >=3.8.0
Requires-Dist: aiohttp (==3.8.1)
